setup.py
HtmlToWord/__init__.py
HtmlToWord/groups.py
HtmlToWord/parser.py
HtmlToWord.egg-info/PKG-INFO
HtmlToWord.egg-info/SOURCES.txt
HtmlToWord.egg-info/dependency_links.txt
HtmlToWord.egg-info/requires.txt
HtmlToWord.egg-info/top_level.txt
HtmlToWord/elements/Base.py
HtmlToWord/elements/Headings.py
HtmlToWord/elements/List.py
HtmlToWord/elements/Misc.py
HtmlToWord/elements/Specials.py
HtmlToWord/elements/Table.py
HtmlToWord/elements/Text.py
HtmlToWord/elements/__init__.py
HtmlToWord/elements/styles.py