Metadata-Version: 1.0
Name: HtmlToWord
Version: 0.6.1
Summary: Render HTML to a specific portion of a word document
Home-page: https://github.com/orf/HtmlToWord
Author: Tom
Author-email: tom@tomforb.es
License: UNKNOWN
Platform: UNKNOWN
